Workbook

Sheet About
A1: Shift-Left User Stories — Batch 2
A2: Scope | B2: Recognition engine (PRD Story 8) · Progress weight on the phase (PRD Story 9)
A3: Source | B3: [PRD] Project Structure — Project MTO (Job Costing for Custom Make-to-Order), v5, 8 Sep 2026
A4: Date | B4: 22 Sep 2026
A5: Status | B5: DRAFT — open-question answers are provisional until PM design review
A6: UI phase | B6: UI phase 3 (plan Part 2) · closes prototype gaps P1 and P2
A7: Prototype reference | B7: feat/project-mto — Recognition & billing tab, Structure tab (localhost:4322)
A9: How to use | B9: Story Backlog is Jira-import ready (CSV export). QA writes test cases from Acceptance Criteria (one criterion per row). Error Handling holds exact user copy in English and Indonesian. Validation Rules say Block vs Warn for every rule.
A10: Totals
A11: Stories | B11: =COUNTA('Story Backlog'!B2:B200)
A12: Acceptance criteria | B12: =COUNTA('Acceptance Criteria'!A2:A500)
A13: Story points | B13: =SUM('Story Backlog'!F2:F200)
A14: Open gaps (not closed) | B14: =COUNTA('Gaps & Decisions'!A2:A200)-COUNTIF('Gaps & Decisions'!D2:D200,"Closed*")

Sheet Story Backlog
A1: Issue Type | B1: Story ID | C1: Summary | D1: Description | E1: Priority | F1: Story Points | G1: Epic Link | H1: Labels | I1: Component | J1: Sprint
A2: Story | B2: PW-01 | C2: [PW-01] Progress weight on the phase row and phase drawer | D2: As a Project Manager, I want to set a progress weight on each Level-2 phase, inline and in the add/edit phase drawer, so that Output recognition has its basis in the project structure instead of a separate milestone list. PRD story: 9. Prototype: tabs/StructureTab.vue (weight input, phase drawer). Acceptance criteria: see sheet 'Acceptance Criteria' (PW-01-AC1…AC7). | E2: Highest | F2: 3 | G2: Project MTO — Recognition & billing | H2: project-mto batch-2 prd-story-9 | I2: Structure | J2: Sprint 1
A3: Story | B3: PW-02 | C3: [PW-02] Weight total summary and the 100% gate | D3: As a Project Manager, I want to see at a glance whether my phase weights total exactly 100%, so that I never verify progress or approve a project on weights that don’t add up. PRD story: 9. Prototype: tabs/StructureTab.vue (weight banner), tabs/RecognitionTab.vue. Acceptance criteria: see sheet 'Acceptance Criteria' (PW-02-AC1…AC6). | E3: Highest | F3: 3 | G3: Project MTO — Recognition & billing | H3: project-mto batch-2 prd-story-9 | I3: Structure | J3: Sprint 1
A4: Story | B4: PW-03 | C4: [PW-03] Weight suggestion from RAB | D4: As a Project Manager, I want weights suggested from each phase’s share of the RAB, so that I start from the contract value split instead of guessing, and still decide the final weight. PRD story: 9. Prototype: data/projects.ts suggestedWeight(); tabs/StructureTab.vue applySuggestions(). Acceptance criteria: see sheet 'Acceptance Criteria' (PW-03-AC1…AC6). | E4: High | F4: 3 | G4: Project MTO — Recognition & billing | H4: project-mto batch-2 prd-story-9 | I4: Structure | J4: Sprint 1
A5: Story | B5: PW-04 | C5: [PW-04] Weight integrity when the structure changes | D5: As a Finance/Controller, I want verified weights frozen and structure changes forced back to 100%, so that recognised revenue can never be reopened by editing the structure. PRD story: 9. Prototype: data/projectActions.ts phaseLockReason(), reconfirmWeights(). Acceptance criteria: see sheet 'Acceptance Criteria' (PW-04-AC1…AC6). | E5: High | F5: 5 | G5: Project MTO — Recognition & billing | H5: project-mto batch-2 prd-story-9 | I5: Structure | J5: Sprint 2
A6: Story | B6: REC-01 | C6: [REC-01] One recognition method and measure, locked at approval | D6: As a Finance/Controller, I want each project to carry exactly one recognition method and measure that locks at approval, so that the accounting basis can’t drift after revenue starts moving. PRD story: 8. Prototype: data/projectActions.ts approveProject(), reopenProject(); ProjectDetailPage.vue header. Acceptance criteria: see sheet 'Acceptance Criteria' (REC-01-AC1…AC6). | E6: Highest | F6: 5 | G6: Project MTO — Recognition & billing | H6: project-mto batch-2 prd-story-8 | I6: Project | J6: Sprint 1
A7: Story | B7: REC-02 | C7: [REC-02] Two clocks: recognition and billing ledgers with WIP position | D7: As a Finance/Controller, I want recognised revenue and billed-to-date kept as separate postings with WIP as the reconciling balance, so that an overbilled or underbilled job is visible, and the down-payment case is representable. PRD story: 8. Prototype: data/projectRecognition.ts (recognitionPostings, projectInvoices, wipPosition); tabs/RecognitionTab.vue. Acceptance criteria: see sheet 'Acceptance Criteria' (REC-02-AC1…AC7). | E7: Highest | F7: 8 | G7: Project MTO — Recognition & billing | H7: project-mto batch-2 prd-story-8 | I7: Recognition | J7: Sprint 2
A8: Story | B8: REC-03 | C8: [REC-03] Verify a phase by BAST — recognition only, no invoice | D8: As a Project Manager, I want to record the BAST for a phase and have its progress weight recognised, so that revenue follows third-party evidence of progress, independent of the billing schedule. PRD story: 8, 9. Prototype: data/projectActions.ts verifyPhase(); tabs/RecognitionTab.vue verify modal. Acceptance criteria: see sheet 'Acceptance Criteria' (REC-03-AC1…AC6). | E8: Highest | F8: 5 | G8: Project MTO — Recognition & billing | H8: project-mto batch-2 prd-story-8-9 | I8: Recognition | J8: Sprint 2
A9: Story | B9: REC-04 | C9: [REC-04] Output · unit recognition run | D9: As a Finance/Controller, I want % complete computed from confirmed ÷ planned units and a run that posts the difference, so that unit-measured jobs recognise revenue as units are produced or delivered. PRD story: 8. Prototype: data/projectRecognition.ts unitProgress(), recognitionDue(); projectActions.ts runRecognition(). Acceptance criteria: see sheet 'Acceptance Criteria' (REC-04-AC1…AC6). | E9: High | F9: 5 | G9: Project MTO — Recognition & billing | H9: project-mto batch-2 prd-story-8 | I9: Recognition | J9: Sprint 3
A10: Story | B10: REC-05 | C10: [REC-05] Input (cost-to-cost) recognition run | D10: As a Finance/Controller, I want % complete = actual cost ÷ budget, recalculating live as cost posts, so that cost-to-cost jobs recognise revenue in step with the work actually done. PRD story: 8. Prototype: data/projectRecognition.ts percentComplete() input branch. Acceptance criteria: see sheet 'Acceptance Criteria' (REC-05-AC1…AC6). | E10: High | F10: 5 | G10: Project MTO — Recognition & billing | H10: project-mto batch-2 prd-story-8 | I10: Recognition | J10: Sprint 3
A11: Story | B11: REC-06 | C11: [REC-06] T&M: bill / write-down / write-up decision per entry | D11: As a Finance/Controller, I want every unbilled time entry to carry a bill, write-down or write-up decision before invoicing, so that what reaches the customer is a deliberate decision, not a raw timesheet dump. PRD story: 8. Prototype: tabs/RecognitionTab.vue T&M table; projectActions.ts setTmDecision(). Acceptance criteria: see sheet 'Acceptance Criteria' (REC-06-AC1…AC5). | E11: High | F11: 5 | G11: Project MTO — Recognition & billing | H11: project-mto batch-2 prd-story-8 | I11: Recognition | J11: Sprint 4
A12: Story | B12: REC-07 | C12: [REC-07] T&M: invoice decided entries (billing + recognition as two postings) | D12: As a Finance/Controller, I want to invoice all decided entries in one action that still creates two separate postings, so that T&M billing is fast while the two-clock model stays intact. PRD story: 8. Prototype: projectActions.ts invoiceTm(). Acceptance criteria: see sheet 'Acceptance Criteria' (REC-07-AC1…AC4). | E12: High | F12: 3 | G12: Project MTO — Recognition & billing | H12: project-mto batch-2 prd-story-8 | I12: Recognition | J12: Sprint 4
A13: Story | B13: REC-08 | C13: [REC-08] Contract billing terms and term invoices (billing only) | D13: As a Finance/Controller, I want to issue invoices from the contract’s own terms, separately from recognition, so that down payments and progress terms bill on the contract’s clock without distorting recognised revenue. PRD story: 8, 9. Prototype: data/projectRecognition.ts billingTerms; projectActions.ts issueTermInvoice(). Acceptance criteria: see sheet 'Acceptance Criteria' (REC-08-AC1…AC7). | E13: Highest | F13: 8 | G13: Project MTO — Recognition & billing | H13: project-mto batch-2 prd-story-8-9 | I13: Billing | J13: Sprint 3

Sheet Acceptance Criteria
A1: Criterion ID | B1: Story | C1: Type | D1: Given / When / Then | E1: Test case status
A2: PW-01-AC1 | B2: PW-01 | C2: Happy path | D2: Given an Output · milestone project at depth 3, When I open the Structure tab, Then every phase row shows a Progress weight input with a % suffix. | E2: Not written
A3: PW-01-AC2 | B3: PW-01 | C3: Happy path | D3: Given the add or edit phase drawer on an Output · milestone project, Then a Progress weight field is shown and saving stores it on the phase. | E3: Not written
A4: PW-01-AC3 | B4: PW-01 | C4: Happy path | D4: Given I type a weight inline and leave the field or press Enter, Then the weight saves and the total summary (PW-02) updates without a page reload. | E4: Not written
A5: PW-01-AC4 | B5: PW-01 | C5: Edge | D5: Given a depth-1 project (auto phase), Then no weight input is shown anywhere. | E5: Not written
A6: PW-01-AC5 | B6: PW-01 | C6: Edge | D6: Given a T&M, Input or Output · unit project, Then no weight input is shown. | E6: Not written
A7: PW-01-AC6 | B7: PW-01 | C7: Audit | D7: Given a weight change, Then an audit entry records phase, old and new weight, actor and time. | E7: Not written
A8: PW-01-AC7 | B8: PW-01 | C8: Edge | D8: Given a verified phase, Then its weight is shown read-only with a Verified badge (enforced in PW-04). | E8: Not written
A9: PW-02-AC1 | B9: PW-02 | C9: Happy path | D9: Given weights that total 100%, Then a green summary reads “Progress weight total: 100%”. | E9: Not written
A10: PW-02-AC2 | B10: PW-02 | C10: Happy path | D10: Given weights that don’t total 100%, Then a red summary states the total and the difference (“Short by 5%” / “Over by 2,5%”). | E10: Not written
A11: PW-02-AC3 | B11: PW-02 | C11: Gate | D11: Given the total is not 100%, When I try to verify a phase (REC-03), Then verification is blocked and the reason names the current total. | E11: Not written
A12: PW-02-AC4 | B12: PW-02 | C12: Gate | D12: Given a Draft Output · milestone project whose total is not 100%, When Finance tries to approve it, Then approval is refused with the same reason. | E12: Not written
... A73: REC-08-AC7 | B73: REC-08 | C73: Rule | D73: Given terms that don’t align with phases (IPB: DP 30% / progress 50% / settlement 20% vs 5 phases), Then nothing tries to map terms to phases. | E73: Not written

Sheet Validation Rules
A1: Rule ID | B1: Story | C1: Rule | D1: Block / Warn / Format
A2: PW-01-VR1 | B2: PW-01 | C2: Weight is a number from 0 to 100, at most 2 decimal places. | D2: Block
A3: PW-01-VR2 | B3: PW-01 | C3: Accepts comma or dot as decimal separator; displays in id-ID format (50,8%). | D3: Format
A4: PW-01-VR3 | B4: PW-01 | C4: Weight input exists only when method = Output and measure = milestone and the phase is not auto. | D4: Block
A5: PW-01-VR4 | B5: PW-01 | C5: Editing is allowed while the project is Draft or Active; closed projects are read-only. | D5: Block
A6: PW-01-VR5 | B6: PW-01 | C6: Tenant guard: the phase must belong to a project of the signed-in company (OQ17). | D6: Block
A7: PW-02-VR1 | B7: PW-02 | C7: Total = sum of non-auto phase weights, compared at 2 decimal places; exactly 100.00 passes. | D7: Block
A8: PW-02-VR2 | B8: PW-02 | C8: The gate uses the same computed total that the summary displays. | D8: Block
A9: PW-02-VR3 | B9: PW-02 | C9: Summary recalculates on every weight save, phase add and phase delete. | D9: Format
A10: PW-03-VR1 | B10: PW-03 | C10: Suggestion source is RAB (contract side), never RAP (cost plan) — using cost share would run Input under the name Output. | D10: Block
A11: PW-03-VR2 | B11: PW-03 | C11: Verified phases are excluded from applying suggestions. | D11: Block
A12: PW-03-VR3 | B12: PW-03 | C12: Rounded suggestions may not total exactly 100%; the PW-02 gate still applies. | D12: Warn
... A46: REC-08-VR4 | B46: REC-08 | C46: Draft projects can’t bill. | D46: Block

Sheet Error Handling
A1: Error ID | B1: Story | C1: Scenario | D1: User copy (EN) | E1: User copy (ID)
A2: PW-01-E1 | B2: PW-01 | C2: Value outside 0–100 | D2: Enter a weight between 0% and 100%. | E2: Isi bobot antara 0% dan 100%.
A3: PW-01-E2 | B3: PW-01 | C3: More than 2 decimals | D3: Use up to 2 decimal places. | E3: Gunakan maksimal 2 angka desimal.
A4: PW-01-E3 | B4: PW-01 | C4: Project closed | D4: This project is closed, so weights can’t change. | E4: Proyek ini sudah ditutup, jadi bobot tidak dapat diubah.
A5: PW-02-E1 | B5: PW-02 | C5: Verify with total ≠ 100% | D5: Progress weights total {total}, not 100%. Fix them on the Structure tab before verifying. | E5: Total bobot progres {total}, bukan 100%. Perbaiki di tab Struktur sebelum memverifikasi.
A6: PW-02-E2 | B6: PW-02 | C6: Approve with total ≠ 100% | D6: Progress weights total {total}. Set them to 100% before approving. | E6: Total bobot progres {total}. Atur hingga 100% sebelum menyetujui.
A7: PW-02-E3 | B7: PW-02 | C7: Milestone project at depth 1 | D7: Milestone-measured Output needs phases — a depth-1 project can’t carry progress weight. Add the first phase. | E7: Output berbasis milestone memerlukan fase — proyek kedalaman 1 tidak dapat menampung bobot progres. Tambahkan fase pertama.
A8: PW-03-E1 | B8: PW-03 | C8: No RAB values | D8: Enter each phase’s RAB value to get a suggestion (phase RAB ÷ total RAB), then adjust. | E8: Isi nilai RAB tiap fase untuk mendapat saran (RAB fase ÷ total RAB), lalu sesuaikan.
A9: PW-03-E2 | B9: PW-03 | C9: Negative RAB | D9: RAB value can’t be negative. | E9: Nilai RAB tidak boleh negatif.
A10: PW-04-E1 | B10: PW-04 | C10: Change a verified phase | D10: This phase is verified (BAST recorded), so it can’t be changed. | E10: Fase ini sudah terverifikasi (BAST tercatat), jadi tidak dapat diubah.
A11: PW-04-E2 | B11: PW-04 | C11: Reconfirm with total ≠ 100% | D11: Weights total {total}. They must total 100% of the new contract value. | E11: Total bobot {total}. Totalnya harus 100% dari nilai kontrak baru.
A12: PW-04-E3 | B12: PW-04 | C12: Verify while reweight required | D12: The contract value changed. Reconfirm the unverified weights to 100% of the new value before verifying. | E12: Nilai kontrak berubah. Konfirmasi ulang bobot yang belum terverifikasi ke 100% dari nilai baru sebelum memverifikasi.
... A32: REC-08-E3 | B32: REC-08 | C32: Trigger not met (warning) | D32: This term’s trigger isn’t met yet ({trigger}). You can still bill it if the customer agreed. | E32: Pemicu termin ini belum terpenuhi ({trigger}). Anda tetap dapat menagihnya jika pelanggan setuju.

Sheet Dependencies
A1: Dependency ID | B1: Story | C1: Depends on | D1: Hard / Soft
A2: PW-01-D1 | B2: PW-01 | C2: Phase entity and Structure tab (UI phase 1) | D2: Hard
A3: PW-01-D2 | B3: PW-01 | C3: Audit writer (UI phase 0) | D3: Hard
A4: PW-02-D1 | B4: PW-02 | C4: PW-01 | D4: Hard
A5: PW-02-D2 | B5: PW-02 | C5: Project approval gate (UI phase 2, Story 7) | D5: Soft
A6: PW-03-D1 | B6: PW-03 | C6: PW-01 | D6: Hard
A7: PW-03-D2 | B7: PW-03 | C7: Approved RAB per phase — from Budget setup (UI phase 2) or manual entry | D7: Soft
A8: PW-04-D1 | B8: PW-04 | C8: PW-02 | D8: Hard
A9: PW-04-D2 | B9: PW-04 | C9: REC-03 (verified state) | D9: Hard
A10: PW-04-D3 | B10: PW-04 | C10: Change order approval (batch 5, Story 12) raises the reweight flag | D10: Soft
A11: REC-01-D1 | B11: REC-01 | C11: Create flow (UI phase 1, Story 1) | D11: Hard
A12: REC-01-D2 | B12: REC-01 | C12: Approval gate (UI phase 2, Story 7) | D12: Hard
... A33: REC-08-D3 | B33: REC-08 | C33: REC-02 | D33: Hard

Sheet Observability
A1: Signal ID | B1: Story | C1: Type | D1: Event / metric / log
A2: PW-01-O1 | B2: PW-01 | C2: Mixpanel | D2: project_weight_edited {project_id, phase_id, from, to, source: inline|drawer}
A3: PW-01-O2 | B3: PW-01 | C3: Audit | D3: kind=structure: “Progress weight on phase {name}: {from} → {to}”
A4: PW-01-O3 | B4: PW-01 | C4: Metric | D4: Save latency p95 ≤ 300 ms (OQ18 proposal)
A5: PW-02-O1 | B5: PW-02 | C5: Mixpanel | D5: project_weight_gate_blocked {project_id, total, action: verify|approve}
A6: PW-02-O2 | B6: PW-02 | C6: Metric | D6: Count of blocked verifications per week — a proxy for weight hygiene
A7: PW-03-O1 | B7: PW-03 | C7: Mixpanel | D7: project_weight_suggestion_applied {project_id, phases_changed}
A8: PW-03-O2 | B8: PW-03 | C8: Audit | D8: kind=structure: “Applied suggested progress weights (phase RAB ÷ total RAB)”
A9: PW-04-O1 | B9: PW-04 | C9: Mixpanel | D9: project_weights_reconfirmed {project_id, contract_value}
A10: PW-04-O2 | B10: PW-04 | C10: Audit | D10: kind=structure: deletions, reconfirm with new contract value
A11: REC-01-O1 | B11: REC-01 | C11: Mixpanel | D11: project_method_locked {project_id, method, measure}; project_method_reopened {project_id}
A12: REC-01-O2 | B12: REC-01 | C12: Audit | D12: kind=approval and kind=method_reopen with reason
... A27: REC-08-O2 | B27: REC-08 | C27: Audit | D27: kind=billing: “Issued term invoice {no} — {term} ({amount}). No revenue recognised.”

Sheet Coverage Matrix
A1: PRD criterion | B1: Source | C1: PRD text | D1: Covered by
A2: S8-1 | B2: 8 | C2: T&M: each unbilled entry carries a bill / write-down / write-up decision before invoicing | D2: REC-06, REC-07
A3: S8-2 | B3: 8 | C3: Input: % complete = actual cost ÷ budget, applied to contract value, recalculating as cost posts | D3: REC-05
A4: S8-3 | B4: 8 | C4: Output · milestone: % complete = sum of achieved phases’ weights | D4: REC-03, PW-02
A5: S8-4 | B5: 8 | C5: Output · unit: % complete = confirmed ÷ planned units across work packages | D5: REC-04
A6: S8-5 | B6: 8 | C6: One method and one measure per project, locked at approval, no mixing | D6: REC-01
A7: S8-6 | B7: 8 | C7: Recognised and billed shown separately with WIP as the reconciling balance | D7: REC-02
A8: S8-7 | B8: 8 | C8: Verifying progress does not issue an invoice in the same posting (P1) | D8: REC-03, REC-07, REC-08
A9: S9-1 | B9: 9 | C9: Level-2 row has a progress weight, also in add and edit phase drawers | D9: PW-01
A10: S9-2 | B10: 9 | C10: Total summary green at 100%, red otherwise with the difference; verification blocked | D10: PW-02
A11: S9-3 | B11: 9 | C11: Weights suggested as phase RAB ÷ total RAB, editable | D11: PW-03
A12: S9-4 | B12: 9 | C12: No weight input on a depth-1 auto phase | D12: PW-01
... A25: QA-P2e | B25: QA | C25: Verified phase cannot be deleted or reweighted | D25: PW-04

Sheet Sprint Readiness
A1: Story | B1: Title | C1: Sprint | D1: Points | E1: Criteria | F1: Valuable | G1: Small | H1: Independent | I1: Open decisions | J1: Ready?
A2: PW-01 | B2: Progress weight on the phase row and phase drawer | C2: Sprint 1 | D2: 3 | E2: =COUNTIF('Acceptance Criteria'!B:B,A2) | F2: Yes | G2: Yes | H2: Yes | I2: — | J2: =IF(I2="—","Ready","Blocked by "&I2)
A3: PW-02 | B3: Weight total summary and the 100% gate | C3: Sprint 1 | D3: 3 | E3: =COUNTIF('Acceptance Criteria'!B:B,A3) | F3: Yes | G3: Yes | H3: Within batch only | I3: — | J3: =IF(I3="—","Ready","Blocked by "&I3)
A4: PW-03 | B4: Weight suggestion from RAB | C4: Sprint 1 | D4: 3 | E4: =COUNTIF('Acceptance Criteria'!B:B,A4) | F4: Yes | G4: Yes | H4: Within batch only | I4: — | J4: =IF(I4="—","Ready","Blocked by "&I4)
A5: PW-04 | B5: Weight integrity when the structure changes | C5: Sprint 2 | D5: 5 | E5: =COUNTIF('Acceptance Criteria'!B:B,A5) | F5: Yes | G5: Yes | H5: Within batch only | I5: — | J5: =IF(I5="—","Ready","Blocked by "&I5)
A6: REC-01 | B6: One recognition method and measure, locked at approval | C6: Sprint 1 | D6: 5 | E6: =COUNTIF('Acceptance Criteria'!B:B,A6) | F6: Yes | G6: Yes | H6: Yes | I6: — | J6: =IF(I6="—","Ready","Blocked by "&I6)
A7: REC-02 | B7: Two clocks: recognition and billing ledgers with WIP position | C7: Sprint 2 | D7: 8 | E7: =COUNTIF('Acceptance Criteria'!B:B,A7) | F7: Yes | G7: Watch (8 pts) | H7: Yes | I7: G1, G5 | J7: =IF(I7="—","Ready","Blocked by "&I7)
A8: REC-03 | B8: Verify a phase by BAST — recognition only, no invoice | C8: Sprint 2 | D8: 5 | E8: =COUNTIF('Acceptance Criteria'!B:B,A8) | F8: Yes | G8: Yes | H8: Within batch only | I8: G5 | J8: =IF(I8="—","Ready","Blocked by "&I8)
A9: REC-04 | B9: Output · unit recognition run | C9: Sprint 3 | D9: 5 | E9: =COUNTIF('Acceptance Criteria'!B:B,A9) | F9: Yes | G9: Yes | H9: Within batch only | I9: G5, G7 | J9: =IF(I9="—","Ready","Blocked by "&I9)
A10: REC-05 | B10: Input (cost-to-cost) recognition run | C10: Sprint 3 | D10: 5 | E10: =COUNTIF('Acceptance Criteria'!B:B,A10) | F10: Yes | G10: Yes | H10: Within batch only | I10: G3, G5 | J10: =IF(I10="—","Ready","Blocked by "&I10)
A11: REC-06 | B11: T&M: bill / write-down / write-up decision per entry | C11: Sprint 4 | D11: 5 | E11: =COUNTIF('Acceptance Criteria'!B:B,A11) | F11: Yes | G11: Yes | H11: Within batch only | I11: G5 | J11: =IF(I11="—","Ready","Blocked by "&I11)
A12: REC-07 | B12: T&M: invoice decided entries (billing + recognition as two postings) | C12: Sprint 4 | D12: 3 | E12: =COUNTIF('Acceptance Criteria'!B:B,A12) | F12: Yes | G12: Yes | H12: Within batch only | I12: G5 | J12: =IF(I12="—","Ready","Blocked by "&I12)
A13: REC-08 | B13: Contract billing terms and term invoices (billing only) | C13: Sprint 3 | D13: 8 | E13: =COUNTIF('Acceptance Criteria'!B:B,A13) | F13: Yes | G13: Watch (8 pts) | H13: Within batch only | I13: G5, G8, OQ11 | J13: =IF(I13="—","Ready","Blocked by "&I13)
A15: Points by sprint
A16: Sprint 1 | B16: Foundation — Smallest, no cross-module dependency; unblocks every other story. | D16: =SUMIFS(D$2:D$13,C$2:C$13,A16)
A17: Sprint 2 | B17: Two-clock ledger + milestone recognition — Needs G1 and G5 decided before estimation. Closes P1 and P2 for milestone projects. | D17: =SUMIFS(D$2:D$13,C$2:C$13,A17)
A18: Sprint 3 | B18: Billing terms + unit / input runs — Needs contract-module terms (OQ11) and a budget baseline (UI phase 2). | D18: =SUMIFS(D$2:D$13,C$2:C$13,A18)
A19: Sprint 4 | B19: T&M — Needs Timesheet module entries with project lines. | D19: =SUMIFS(D$2:D$13,C$2:C$13,A19)
A20: Total | D20: =SUM(D16:D19)

Sheet Gaps & Decisions
A1: Gap ID | B1: Question | C1: Recommendation | D1: Status | E1: Affects | F1: Owner
A2: G1 | B2: GL posting spec for recognition and billing is not written (PRD constraint). | C2: Recognition: Dr Contract asset (unbilled revenue) / Cr Revenue. Billing: Dr Accounts receivable / Cr Contract asset up to its balance, remainder Cr Contract liability. Report the net per project as WIP. | D2: Estimation-blocking | E2: REC-02 | F2: Finance + Engineering
A3: G5 | B3: Which date recognition and billing post on, and whether backdating is allowed. | C3: Default today; may be backdated only within an open accounting period; closed periods are refused. | D3: Estimation-blocking | E3: REC-02…08 | F3: Finance
A4: G3 | B4: Input method denominator: include phase reserves or only allocated budget? | C4: Current approved cost budget including reserves (what the prototype does). Finance to confirm. | D4: Needs decision | E4: REC-05 | F4: Finance
A5: G4 | B5: Input method when actual cost exceeds budget (onerous contract / loss provision). | C5: Cap % at 100% and warn; loss provision is out of MVP scope and logged as a future story. | D5: Scope note | E5: REC-05 | F5: Product + Finance
A6: G6 | B6: How a wrong recognition (e.g. a BAST recorded in error) is corrected. | C6: Finance-only reversal posting with a reason; the phase returns to unverified; never delete a posting. | D6: New requirement | E6: REC-02, REC-03 | F6: Product + Finance
A7: G7 | B7: Source of confirmed units for Output · unit. | C7: Production: WO output received. Service: BAST quantity. Manual edits are audited. | D7: Needs decision | E7: REC-04 | F7: Product + Production
A8: G8 | B8: Term amount after a change order changes the contract value. | C8: Uninvoiced terms recalculate on the new value; invoiced terms never change. Depends on OQ11 (terms owned by the contract module). | D8: Needs decision | E8: REC-08 | F8: Product
A9: G9 | B9: Precision of progress weights. | C9: Max 2 decimals; the 100% check compares at 2 dp. | D9: Closed (assumed) | E9: PW-01, PW-02 | F9: Product
A10: G10 | B10: Is a reason required for T&M write-down / write-up? | C10: Yes, 5–300 characters. The prototype didn’t require one — added as a new requirement. | D10: New requirement | E10: REC-06 | F10: Product
A11: G11 | B11: Who may verify a phase by BAST. | C11: PM or Finance; Finance alone may reverse (G6). | D11: Closed (assumed) | E11: REC-03 | F11: Product
A12: G12 | B12: Currency. | C12: IDR only in MVP; multi-currency contracts out of scope. | D12: Scope note | E12: All | F12: Product
... A15: OQ11 | B15: Are billing terms specified in this PRD or the contract module? | C15: Provisional: the contract/SO module owns them; this module reads. | D15: Provisional | E15: REC-08 | F15: Product
